README.md
requirements.txt
setup.cfg
setup.py
huawei_modem_py_api_client_through_proxy.egg-info/PKG-INFO
huawei_modem_py_api_client_through_proxy.egg-info/SOURCES.txt
huawei_modem_py_api_client_through_proxy.egg-info/dependency_links.txt
huawei_modem_py_api_client_through_proxy.egg-info/requires.txt
huawei_modem_py_api_client_through_proxy.egg-info/top_level.txt
huaweisms/__init__.py
huaweisms/api/__init__.py
huaweisms/api/common.py
huaweisms/api/config.py
huaweisms/api/device.py
huaweisms/api/dialup.py
huaweisms/api/monitoring.py
huaweisms/api/sms.py
huaweisms/api/user.py
huaweisms/api/ussd.py
huaweisms/api/webserver.py
huaweisms/api/wlan.py
huaweisms/xml/__init__.py
huaweisms/xml/util.py