Metadata-Version: 2.1
Name: huawei-modem-py-api-client-through-proxy
Version: 0.0.7
Summary: huaweisms is a python api client for Huawei Modems.
Home-page: https://github.com/growield/huawei-modem-py-api-client-through-proxy
Author: Pablo Santa Cruz, Mkhanyisi Madlavana
Author-email: pablo@roshka.com.py, mkhanyisi@gmail.com
License: UNKNOWN
Download-URL: https://github.com/growield/huawei-modem-py-api-client-through-proxy/tree/0.0.7
Keywords: Huawei,Modem,HTTP API Client,API Client,Router
Platform: UNKNOWN
Classifier: Development Status :: 5 - Production/Stable
Classifier: Intended Audience :: Developers
Classifier: Natural Language :: English
Classifier: Programming Language :: Python :: 3.5
Classifier: Programming Language :: Python :: 3.6
Classifier: Programming Language :: Python :: 3.7
Classifier: License :: OSI Approved :: MIT License
Classifier: Operating System :: MacOS
Classifier: Operating System :: POSIX :: Linux
Classifier: Operating System :: Microsoft :: Windows
Classifier: Topic :: Software Development :: Version Control :: Git
Classifier: Programming Language :: Python :: Implementation :: CPython
Provides-Extra: linting
Provides-Extra: testing
